conc_test_report/__init__.py
conc_test_report/c_kontur.py
conc_test_report/c_mcelhanney.py
conc_test_report/company.py
conc_test_report/definitions.py
conc_test_report/generator.py
conc_test_report/parser.py
conc_test_report/stru_checks.py
conc_test_report-0.0.1.dist-info/LICENSE
conc_test_report-0.0.1.dist-info/WHEEL
conc_test_report-0.0.1.dist-info/METADATA
conc_test_report-0.0.1.dist-info/RECORD
