Metadata-Version: 2.1
Name: conc_test_report
Version: 0.0.1
Summary: Generate a concise and brief summary of all concrete test result PDFs, to aid in fast and efficient review
Author-email: Arun Kishore <pypi@rpakishore.co.in>
Classifier: License :: OSI Approved :: MIT License
Requires-Dist: pytest>=7.2.1
Requires-Dist: pandas>=1.5.3
Requires-Dist: pdfplumber==0.7.6
Project-URL: Home, https://github.com/rpakishore/Concrete_Test_Results
